aws_web_builder/__init__.py
aws_web_builder/aws_acm.py
aws_web_builder/aws_cdn.py
aws_web_builder/aws_route53.py
aws_web_builder/aws_s3.py
aws_web_builder/aws_util.py
aws_web_builder/aws_web_builder.py
aws_web_builder-0.1.dist-info/METADATA
aws_web_builder-0.1.dist-info/RECORD
aws_web_builder-0.1.dist-info/WHEEL
aws_web_builder-0.1.dist-info/entry_points.txt
aws_web_builder-0.1.dist-info/top_level.txt
