Metadata-Version: 2.1
Name: aws-web-builder
Version: 0.1
Summary: Tool used to deploy static websites to AWS S3.
Home-page: https://github.com/shlubz/aws_web_builder
Author: Shlubz
Author-email: jayboy229@gmail.com
License: GPLv3
Platform: UNKNOWN
Classifier: Programming Language :: Python :: 3
Classifier: License :: OSI Approved :: MIT License
Classifier: Operating System :: OS Independent
Requires-Dist: click
Requires-Dist: boto3
